paneltime_mp/__init__.py
paneltime_mp/info.py
paneltime_mp/slave.py
paneltime_mp/transact.py
paneltime_mp-0.0.2.dist-info/LICENSE
paneltime_mp-0.0.2.dist-info/METADATA
paneltime_mp-0.0.2.dist-info/WHEEL
paneltime_mp-0.0.2.dist-info/top_level.txt
paneltime_mp-0.0.2.dist-info/RECORD
